{
  "version": 2,
  "position": 4,
  "lessons": [
    "A\nB\nC\nD",
    "A == B",
    "AB => D C",
    "E\nACE => B D"
  ],
  "curriculum_file": "curricula/conflict-drill.md",
  "current_label": null,
  "lesson_submitted": [
    "1",
    "2",
    "3",
    "4"
  ],
  "lesson_satisfied": [
    "1",
    "2",
    "3",
    "4"
  ],
  "submitted": [
    [
      2,
      []
    ],
    [
      2,
      [
        4
      ]
    ],
    [
      4,
      []
    ],
    [
      4,
      [
        2
      ]
    ],
    [
      6,
      [
        2,
        4
      ]
    ],
    [
      6,
      [
        16,
        8
      ]
    ],
    [
      8,
      []
    ],
    [
      16,
      []
    ],
    [
      32,
      []
    ],
    [
      42,
      [
        2,
        8,
        32
      ]
    ],
    [
      42,
      [
        4,
        16
      ]
    ]
  ],
  "satisfied": [
    [
      2,
      []
    ],
    [
      2,
      [
        4
      ]
    ],
    [
      2,
      [
        6
      ]
    ],
    [
      4,
      []
    ],
    [
      4,
      [
        2
      ]
    ],
    [
      6,
      [
        2
      ]
    ],
    [
      6,
      [
        2,
        4
      ]
    ],
    [
      6,
      [
        8
      ]
    ],
    [
      6,
      [
        16
      ]
    ],
    [
      8,
      []
    ],
    [
      16,
      []
    ],
    [
      32,
      []
    ],
    [
      42,
      [
        2,
        8,
        32
      ]
    ],
    [
      42,
      [
        4,
        16
      ]
    ]
  ],
  "pending": [],
  "event_log": [
    {
      "timestamp": "2026-06-08T06:30:02.436524+00:00",
      "type": "session_start",
      "data": {
        "goal": null
      }
    },
    {
      "timestamp": "2026-06-08T06:30:02.437879+00:00",
      "type": "lesson_complete",
      "data": {
        "position": 0
      }
    },
    {
      "timestamp": "2026-06-08T06:30:02.438989+00:00",
      "type": "lesson_complete",
      "data": {
        "position": 1
      }
    },
    {
      "timestamp": "2026-06-08T06:30:49.507094+00:00",
      "type": "reactive_scaffolding",
      "data": {
        "confidence": 0.72,
        "source": "( Scaffold for Event 1: bridge underfit gap between proposal B => A B and expectation AB > D C )\n( Provide the missing relationship expected by the system )\nAB > D C\n( Bridge the canonize B => A B into the AB identity via countersign )\nAB == A B\n( Ensure D and C are connected back to the AB signature )\nD = AB\nC = AB"
      }
    },
    {
      "timestamp": "2026-06-08T06:30:49.507161+00:00",
      "type": "lesson_complete",
      "data": {
        "position": 2
      }
    },
    {
      "timestamp": "2026-06-08T06:31:21.554864+00:00",
      "type": "reactive_scaffolding",
      "data": {
        "confidence": 0.75,
        "source": "(bridging underfit gap: proposal B => B fails to cover expectation AB > D C)\nA\nB\nC\nD\nAB == A B\nAB > D C"
      }
    },
    {
      "timestamp": "2026-06-08T06:31:51.252071+00:00",
      "type": "reactive_scaffolding",
      "data": {
        "confidence": 0.75,
        "source": "( Bridging underfit: AB composite identity and its relationship )\nAB == A B\nAB > D C"
      }
    },
    {
      "timestamp": "2026-06-08T06:32:37.644708+00:00",
      "type": "reactive_scaffolding",
      "data": {
        "confidence": 0.75,
        "source": "( Bridge underfit: proposal A=>A misses relationship AB > D C entirely )\n( Introduce the expected relationship and expand A into AB )\nAB > D C\nAB = A B"
      }
    },
    {
      "timestamp": "2026-06-08T06:32:37.645173+00:00",
      "type": "escalation",
      "data": {
        "reason": "budget_exhaustion",
        "detail": ""
      }
    },
    {
      "timestamp": "2026-06-08T06:32:37.659859+00:00",
      "type": "lesson_complete",
      "data": {
        "position": 3
      }
    },
    {
      "timestamp": "2026-06-08T06:33:30.787971+00:00",
      "type": "reactive_scaffolding",
      "data": {
        "confidence": 0.75,
        "source": "ACE > B D\nACE == AB\nAB => B D"
      }
    },
    {
      "timestamp": "2026-06-08T06:34:58.502336+00:00",
      "type": "reactive_scaffolding",
      "data": {
        "confidence": 0.72,
        "source": "( Bridge underfit: countersign AB with ACE to cover missing C and E bits )\nAB == ACE\n( Establish the expected relationship from ACE to B and D )\nACE > B D\n( Undersign constrains overfit excess, scoping target to B D only )\nACE = B D"
      }
    },
    {
      "timestamp": "2026-06-08T06:35:47.907062+00:00",
      "type": "reactive_scaffolding",
      "data": {
        "confidence": 0.72,
        "source": "(Bridge dual misfit: underfit signature coverage + overfit node excess)\n(Expected relationship establishing ACE as connector of B and D)\nACE > B D\n(Countersign to reconcile proposal signature AB with expected signature ACE)\n(Bidirectional mapping resolves underfit by extending ABs coverage to ACE)\n(And resolves overfit by constraining ABs excess through ACEs structure)\nAB == ACE"
      }
    },
    {
      "timestamp": "2026-06-08T06:36:56.096172+00:00",
      "type": "reactive_scaffolding",
      "data": {
        "confidence": 0.72,
        "source": "(Reassert the expected relationship identity)\nACE > B D\n(Countersign proposal identity AB with expected identity ACE)\n(Resolves overfit by collapsing AB back into the canonical ACE frame)\nAB == ACE\n(Undersign expansion to recover undercovered signature nodes C and E)\n(Addresses underfit by attaching missing bits into the unified identity)\nAB = C E"
      }
    },
    {
      "timestamp": "2026-06-08T06:36:56.096389+00:00",
      "type": "escalation",
      "data": {
        "reason": "budget_exhaustion",
        "detail": ""
      }
    },
    {
      "timestamp": "2026-06-08T06:36:56.158894+00:00",
      "type": "session_end",
      "data": {}
    }
  ]
}